flake8_forelse/__init__.py
flake8_forelse-1.0.0.dist-info/LICENSE
flake8_forelse-1.0.0.dist-info/METADATA
flake8_forelse-1.0.0.dist-info/WHEEL
flake8_forelse-1.0.0.dist-info/entry_points.txt
flake8_forelse-1.0.0.dist-info/top_level.txt
flake8_forelse-1.0.0.dist-info/RECORD
