Metadata-Version: 2.1
Name: flake8-forelse
Version: 1.0.0
Summary: A Flake8 plugin which checks the use of for-else and while-else
Home-page: https://github.com/koviubi56/flake8-forelse
Download-URL: https://github.com/koviubi56/flake8-forelse/releases
Author: Koviubi56
Author-email: koviubi56@duck.com
Maintainer: Koviubi56
Maintainer-email: koviubi56@duck.com
License: GNU GPLv3+
Project-URL: Source, https://github.com/koviubi56/flake8-forelse
Project-URL: Tracker, https://github.com/koviubi56/flake8-forelse/issues
Keywords: flake8,plugin,for,else,forelse,while,whileelse
Classifier: Development Status :: 5 - Production/Stable
Classifier: Environment :: Plugins
Classifier: Framework :: Flake8
Classifier: Intended Audience :: Developers
Classifier: License :: OSI Approved :: GNU General Public License v3 (GPLv3)
Classifier: License :: OSI Approved :: GNU General Public License v3 or later (GPLv3+)
Classifier: Natural Language :: English
Classifier: Operating System :: OS Independent
Classifier: Programming Language :: Python :: 3
Classifier: Programming Language :: Python :: 3 :: Only
Classifier: Programming Language :: Python :: 3.6
Classifier: Programming Language :: Python :: 3.7
Classifier: Programming Language :: Python :: 3.8
Classifier: Programming Language :: Python :: 3.9
Classifier: Programming Language :: Python :: 3.10
Classifier: Programming Language :: Python :: 3.11
Classifier: Typing :: Typed
Requires-Python: >=3.6
License-File: LICENSE
